ehzahumming/__init__.py
ehzahumming/humming.py
ehzahumming-0.2.dist-info/METADATA
ehzahumming-0.2.dist-info/WHEEL
ehzahumming-0.2.dist-info/top_level.txt
ehzahumming-0.2.dist-info/RECORD
