Metadata-Version: 2.1
Name: ehzahumming
Version: 0.2
Summary: A simple utility to generate humming sounds
Home-page: https://github.com/ehzawad/ehzahumming
Author: ehzawad
Author-email: ehzawad@gmail.com
Classifier: License :: OSI Approved :: MIT License
Classifier: Programming Language :: Python
Classifier: Programming Language :: Python :: 3
Classifier: Programming Language :: Python :: 3.6
Classifier: Programming Language :: Python :: 3.7
Classifier: Programming Language :: Python :: 3.8
Classifier: Programming Language :: Python :: 3.9
